samplitude/__init__.py
samplitude/__main__.py
samplitude/_generators.py
samplitude/_samplitude.py
samplitude/_utils.py
samplitude-0.1.0.dist-info/LICENSE
samplitude-0.1.0.dist-info/METADATA
samplitude-0.1.0.dist-info/WHEEL
samplitude-0.1.0.dist-info/entry_points.txt
samplitude-0.1.0.dist-info/top_level.txt
samplitude-0.1.0.dist-info/RECORD
