Metadata-Version: 2.1
Name: samplitude
Version: 0.1.0
Summary: Samplitude (s8e) is a statistical distributions command line tool
Home-page: https://github.com/pgdr/samplitude
Author: PG Drange
Author-email: pgdr@equinor.com
Maintainer: PG Drange <pgdr@equinor.com>
License: GNU GPL v3 or later
Project-URL: Bug Tracker, https://github.com/pgdr/samplitude/issues
Project-URL: Documentation, https://github.com/pgdr/samplitude/blob/master/README.md
Project-URL: Source Code, https://github.com/pgdr/samplitude
Keywords: jinja2 jinja random statistics sample distribution plot
Platform: UNKNOWN
Requires-Dist: numpy (>=1.11)
Requires-Dist: Jinja2
Provides-Extra: complete
Requires-Dist: Jinja2 ; extra == 'complete'
Requires-Dist: matplotlib ; extra == 'complete'
Requires-Dist: numpy (>=1.11) ; extra == 'complete'
Requires-Dist: pandas ; extra == 'complete'
Requires-Dist: scipy ; extra == 'complete'
Provides-Extra: csv
Requires-Dist: numpy (>=1.11) ; extra == 'csv'
Requires-Dist: Jinja2 ; extra == 'csv'
Requires-Dist: pandas ; extra == 'csv'
Provides-Extra: csv_sci
Requires-Dist: numpy (>=1.11) ; extra == 'csv_sci'
Requires-Dist: Jinja2 ; extra == 'csv_sci'
Requires-Dist: pandas ; extra == 'csv_sci'
Requires-Dist: scipy ; extra == 'csv_sci'
Provides-Extra: minimum
Requires-Dist: numpy (>=1.11) ; extra == 'minimum'
Requires-Dist: Jinja2 ; extra == 'minimum'
Provides-Extra: plot
Requires-Dist: numpy (>=1.11) ; extra == 'plot'
Requires-Dist: Jinja2 ; extra == 'plot'
Requires-Dist: matplotlib ; extra == 'plot'
Provides-Extra: sci
Requires-Dist: numpy (>=1.11) ; extra == 'sci'
Requires-Dist: Jinja2 ; extra == 'sci'
Requires-Dist: scipy ; extra == 'sci'
